slurmbench/__init__.py
slurmbench/__main__.py
slurmbench/app.py
slurmbench/bash/__init__.py
slurmbench/bash/create.py
slurmbench/bash/items.py
slurmbench/doc/__init__.py
slurmbench/doc/app.py
slurmbench/doc/environments.py
slurmbench/experiment/__init__.py
slurmbench/experiment/bash/__init__.py
slurmbench/experiment/bash/create.py
slurmbench/experiment/bash/file_system.py
slurmbench/experiment/bash/items.py
slurmbench/experiment/bash/manager.py
slurmbench/experiment/bash/sbatch_template.sh
slurmbench/experiment/checks.py
slurmbench/experiment/errors.py
slurmbench/experiment/file_system.py
slurmbench/experiment/history.py
slurmbench/experiment/in_progress.py
slurmbench/experiment/iter.py
slurmbench/experiment/managers.py
slurmbench/experiment/monitors.py
slurmbench/experiment/report.py
slurmbench/experiment/resolve.py
slurmbench/experiment/resume.py
slurmbench/experiment/run.py
slurmbench/experiment/slurm/__init__.py
slurmbench/experiment/slurm/checks.py
slurmbench/experiment/slurm/file_system.py
slurmbench/experiment/slurm/run.py
slurmbench/experiment/slurm/status.py
slurmbench/experiment/stats.py
slurmbench/help/__init__.py
slurmbench/help/app.py
slurmbench/help/tool_tree.py
slurmbench/module_meta.py
slurmbench/prelude/__init__.py
slurmbench/prelude/app.py
slurmbench/prelude/samples.py
slurmbench/prelude/tool/__init__.py
slurmbench/prelude/tool/app.py
slurmbench/prelude/tool/bash.py
slurmbench/prelude/tool/connector.py
slurmbench/prelude/tool/description.py
slurmbench/prelude/tool/results.py
slurmbench/prelude/topic/__init__.py
slurmbench/prelude/topic/app.py
slurmbench/prelude/topic/description.py
slurmbench/prelude/topic/results.py
slurmbench/prelude/topic/visitor.py
slurmbench/prelude/topics/__init__.py
slurmbench/prelude/topics/visitor.py
slurmbench/py.typed
slurmbench/root_logging.py
slurmbench/samples/__init__.py
slurmbench/samples/bash.py
slurmbench/samples/file_system.py
slurmbench/samples/items.py
slurmbench/samples/missing_inputs.py
slurmbench-0.3.7.dist-info/WHEEL
slurmbench-0.3.7.dist-info/entry_points.txt
slurmbench-0.3.7.dist-info/METADATA
slurmbench-0.3.7.dist-info/RECORD
