Metadata-Version: 2.3
Name: slurmbench
Version: 0.3.7
Summary: SLURM benchmark interface.
Author: vepain
Author-email: vepain <victorepain@disroot.org>
License: # GNU GENERAL PUBLIC LICENSE
Requires-Dist: pyyaml>=6.0,<7.0
Requires-Dist: typer>=0.20,<1.0
Requires-Dist: mermaid-py>=0.8,<1.0
Requires-Dist: rich>=14.2.0
Requires-Python: >=3.13
Project-URL: Repository, https://gitlab.com/vepain/slurmbench-py
Project-URL: Changelog, https://gitlab.com/vepain/slurmbench-py/-/blob/main/CHANGELOG.md
